cognito_confidential/__init__.py
cognito_confidential/authentications.py
cognito_confidential/clients.py
cognito_confidential/config.py
cognito_confidential/exceptions.py
cognito_confidential/models.py
cognito_confidential/parsers.py
cognito_confidential/stores.py
cognito_confidential/validations.py
scalde_cognito_confidential-0.0.3.dist-info/METADATA
scalde_cognito_confidential-0.0.3.dist-info/WHEEL
scalde_cognito_confidential-0.0.3.dist-info/top_level.txt
scalde_cognito_confidential-0.0.3.dist-info/RECORD
